k3log/__init__.py
k3log/log.py
k3log/synopsis.py
k3log-0.1.8.dist-info/licenses/LICENSE
k3log-0.1.8.dist-info/METADATA
k3log-0.1.8.dist-info/WHEEL
k3log-0.1.8.dist-info/top_level.txt
k3log-0.1.8.dist-info/RECORD
